dtera.cp35-win_amd64.pyd
dtera-1.11.dist-info/DESCRIPTION.rst
dtera-1.11.dist-info/METADATA
dtera-1.11.dist-info/RECORD
dtera-1.11.dist-info/WHEEL
dtera-1.11.dist-info/metadata.json
dtera-1.11.dist-info/top_level.txt
