Metadata-Version: 2.0
Name: dtera
Version: 1.11
Summary: Data Mining
Home-page: UNKNOWN
Author: UNKNOWN
Author-email: UNKNOWN
License: UNKNOWN
Platform: UNKNOWN
